pycohttpparser/__init__.py
pycohttpparser/_pycohttpparser.so
pycohttpparser/api.py
pycohttpparser/build.py
pycohttpparser-1.1.0.dist-info/DESCRIPTION.rst
pycohttpparser-1.1.0.dist-info/METADATA
pycohttpparser-1.1.0.dist-info/RECORD
pycohttpparser-1.1.0.dist-info/WHEEL
pycohttpparser-1.1.0.dist-info/metadata.json
pycohttpparser-1.1.0.dist-info/top_level.txt
