Metadata-Version: 2.0
Name: pycohttpparser
Version: 1.1.0
Summary: Python wrapper for picohttpparser
Home-page: https://github.com/Lukasa/pycohttpparser
Author: Cory Benfield
Author-email: cory@lukasa.co.uk
License: MIT License
Platform: UNKNOWN
Classifier: Development Status :: 4 - Beta
Classifier: Intended Audience :: Developers
Classifier: License :: OSI Approved :: MIT License
Classifier: Programming Language :: Python
Classifier: Programming Language :: Python :: 2
Classifier: Programming Language :: Python :: 2.7
Classifier: Programming Language :: Python :: 3
Classifier: Programming Language :: Python :: 3.4
Requires-Dist: cffi (>=1.0.0)
